vipentium/__init__.py
vipentium/vipentium_runner.py
vipentium/decorators/__init__.py
vipentium/decorators/decorator.py
vipentium/depss/__init__.py
vipentium/depss/dep.py
vipentium/helpers/__init__.py
vipentium/helpers/helper.py
vipentium/plugins/__init__.py
vipentium/plugins/plugin.py
vipentium/plugins/trelloplugin.py
vipentium/reports/__init__.py
vipentium/reports/report.py
vipentium/starter/__init__.py
vipentium/starter/startz.py
vipentium/testcases/__init__.py
vipentium/testcases/coreex.py
vipentium/testcases/testbase.py
vipentium/testcases/testsuite.py
vipentium-1.1.1.dist-info/licenses/LICENSE
vipentium-1.1.1.dist-info/METADATA
vipentium-1.1.1.dist-info/WHEEL
vipentium-1.1.1.dist-info/entry_points.txt
vipentium-1.1.1.dist-info/top_level.txt
vipentium-1.1.1.dist-info/RECORD
