Metadata-Version: 2.4
Name: vipentium
Version: 1.1.1
Summary: Powerful & user-friendly Python testing – streamlined workflows
Home-page: https://suresh-pyhobbyist.github.io/vipentium/
Author: suresh
Classifier: Programming Language :: Python :: 3
Classifier: License :: OSI Approved :: MIT License
Classifier: Operating System :: OS Independent
Requires-Python: >=3.6
License-File: LICENSE
Dynamic: author
Dynamic: classifier
Dynamic: description
Dynamic: description-content-type
Dynamic: home-page
Dynamic: license-file
Dynamic: requires-python
Dynamic: summary
